spatialmeta/__init__.py
spatialmeta/_metadata.py
spatialmeta/_version.py
spatialmeta/test_alignment.py
spatialmeta/data/__init__.py
spatialmeta/data/_dataloader.py
spatialmeta/data/hmdb.csv
spatialmeta/data/zenodo_url.txt
spatialmeta/external/__init__.py
spatialmeta/external/stalign/STalign.py
spatialmeta/external/stalign/__init__.py
spatialmeta/external/stalign/curve_annotator.py
spatialmeta/external/stalign/point_annotator.py
spatialmeta/external/stalign/script.py
spatialmeta/model/__init__.py
spatialmeta/model/_alignment_model.py
spatialmeta/model/_alignment_module.py
spatialmeta/model/_model.py
spatialmeta/model/_moe.py
spatialmeta/model/_primitives.py
spatialmeta/plotting/__init__.py
spatialmeta/plotting/_plotting.py
spatialmeta/plotting/_utils.py
spatialmeta/plotting/core/__init__.py
spatialmeta/plotting/core/wrapper.py
spatialmeta/plotting/plotly/__init__.py
spatialmeta/plotting/plotly/defaults.py
spatialmeta/plotting/plotly/layout.py
spatialmeta/plotting/utils/__init__.py
spatialmeta/plotting/utils/_fit_curve.py
spatialmeta/plotting/utils/utils.py
spatialmeta/preprocess/__init__.py
spatialmeta/preprocess/_creat_hex_grid.py
spatialmeta/preprocess/_metabolite_annotation.py
spatialmeta/preprocess/_preprocess.py
spatialmeta/preprocess/_simple.py
spatialmeta/tool/__init__.py
spatialmeta/util/__init__.py
spatialmeta/util/_classes.py
spatialmeta/util/_decorators.py
spatialmeta/util/_squidpy_spatial_variable_genes.py
spatialmeta/util/_trvae_mmd_loss.py
spatialmeta/util/compat.py
spatialmeta/util/distributions.py
spatialmeta/util/logger.py
spatialmeta/util/loss.py
spatialMETA-0.0.3.0.dist-info/METADATA
spatialMETA-0.0.3.0.dist-info/WHEEL
spatialMETA-0.0.3.0.dist-info/dependency_links.txt
spatialMETA-0.0.3.0.dist-info/top_level.txt
spatialMETA-0.0.3.0.dist-info/RECORD
